{"id":158,"name":"ลพบุรี เขต 4","areaNo":4,"candidates":[{"id":3358,"candidateAreaNo":5,"firstName":"นรินทร์","lastName":"คลังผา","party":"ภูมิใจไทย","partyId":15,"goodVote":41413},{"id":3360,"candidateAreaNo":7,"firstName":"มนัส","lastName":"ไหวพริบ","party":"ก้าวไกล","partyId":116,"goodVote":18421},{"id":3356,"candidateAreaNo":3,"firstName":"อุบลศักดิ์","lastName":"บัวหลวงงาม","party":"เพื่อไทย","partyId":8,"goodVote":18326},{"id":3361,"candidateAreaNo":8,"firstName":"ณพล","lastName":"แสงสกุล","party":"รวมไทยสร้างชาติ","partyId":121,"goodVote":1992},{"id":3359,"candidateAreaNo":6,"firstName":"ณฐพงษ์","lastName":"นรสิงห์","party":"พลังประชารัฐ","partyId":81,"goodVote":664},{"id":3357,"candidateAreaNo":4,"firstName":"ชัยอนันต์","lastName":"มานะกุล","party":"ถิ่นกาขาวชาววิไล","partyId":32,"goodVote":629},{"id":3354,"candidateAreaNo":1,"firstName":"ณัฐธพงษ์","lastName":"บัวบาล","party":"เสรีรวมไทย","partyId":38,"goodVote":504},{"id":3355,"candidateAreaNo":2,"firstName":"ธนสรรค์","lastName":"คงสงฆ์","party":"ประชาธิปัตย์","partyId":1,"goodVote":450},{"id":3362,"candidateAreaNo":9,"firstName":"สุพจน์","lastName":"สมสิงห์","party":"เพื่อชาติ","partyId":41,"goodVote":441},{"id":3364,"candidateAreaNo":11,"firstName":"มนู","lastName":"สุขสม","party":"ไทยภักดี","partyId":123,"goodVote":130},{"id":3365,"candidateAreaNo":12,"firstName":"สมชาย","lastName":"พ่วงเจริญ","party":"คลองไทย","partyId":78,"goodVote":130},{"id":3363,"candidateAreaNo":10,"firstName":"ทรงพล","lastName":"เกียรติวินัยสกุล","party":"เปลี่ยน","partyId":144,"goodVote":93}],"updateTime":"2023-05-28T10:58:07.648652641Z","area":{"totalVotes":83193,"noVotes":1682,"badVotes":4912,"goodVotes":83193},"partyList":{"totalVotes":83045,"noVotes":1030,"badVotes":5712,"goodVotes":83045},"progress":95}