{"id":154,"name":"ราชบุรี เขต 5","areaNo":5,"candidates":[{"id":3311,"candidateAreaNo":3,"firstName":"ชัยทิพย์","lastName":"กมลพันธ์ทิพย์","party":"พลังประชารัฐ","partyId":81,"goodVote":44253},{"id":3309,"candidateAreaNo":1,"firstName":"บุญลือ","lastName":"ประเสริฐโสภา","party":"ภูมิใจไทย","partyId":15,"goodVote":38284},{"id":3318,"candidateAreaNo":10,"firstName":"ธนพจน์","lastName":"ทรัพย์ยอดแก้ว","party":"ก้าวไกล","partyId":116,"goodVote":17095},{"id":3316,"candidateAreaNo":8,"firstName":"ปวันรัตน์","lastName":"เอกอัครอัญธรณ์","party":"เพื่อไทย","partyId":8,"goodVote":6179},{"id":3315,"candidateAreaNo":7,"firstName":"วณิช","lastName":"บุญสอง","party":"รวมไทยสร้างชาติ","partyId":121,"goodVote":2298},{"id":3310,"candidateAreaNo":2,"firstName":"ชวลิต","lastName":"สาลีติ๊ด","party":"ประชาธิปัตย์","partyId":1,"goodVote":783},{"id":3317,"candidateAreaNo":9,"firstName":"นันทวรรณ","lastName":"มาศิริ","party":"ไทยภักดี","partyId":123,"goodVote":269},{"id":3313,"candidateAreaNo":5,"firstName":"ณัฐธยาน์","lastName":"ลิ้มวิลัย","party":"เสรีรวมไทย","partyId":38,"goodVote":247},{"id":3319,"candidateAreaNo":11,"firstName":"สายชล","lastName":"มิ่งสมร","party":"คลองไทย","partyId":78,"goodVote":231},{"id":3312,"candidateAreaNo":4,"firstName":"โชคชัย","lastName":"เอี่ยมภูมิ","party":"ชาติพัฒนากล้า","partyId":10,"goodVote":223},{"id":3314,"candidateAreaNo":6,"firstName":"ตฤณฤทธ","lastName":"เทพประสิทธิ์","party":"ไทยสร้างไทย","partyId":118,"goodVote":143}],"updateTime":"2023-05-28T10:58:31.789426005Z","area":{"totalVotes":110005,"noVotes":1496,"badVotes":3292,"goodVotes":110005},"partyList":{"totalVotes":108474,"noVotes":1546,"badVotes":4773,"goodVotes":108474},"progress":95}