{"updateTime":"2023-05-28T10:58:33.091815327Z","id":58,"name":"นครปฐม","progress":95,"area":{"totalVotes":583225,"noVotes":15022,"badVotes":19527,"goodVotes":583225},"partyList":{"totalVotes":588544,"noVotes":9329,"badVotes":19901,"goodVotes":588544},"parties":[{"id":116,"seat":2},{"id":162,"seat":3},{"id":121,"seat":1},{"id":8,"seat":0},{"id":15,"seat":0},{"id":81,"seat":0},{"id":1,"seat":0},{"id":38,"seat":0},{"id":118,"seat":0},{"id":10,"seat":0},{"id":123,"seat":0},{"id":75,"seat":0},{"id":69,"seat":0},{"id":167,"seat":0},{"id":78,"seat":0},{"id":2,"seat":0},{"id":6,"seat":0},{"id":12,"seat":0},{"id":17,"seat":0},{"id":24,"seat":0},{"id":28,"seat":0},{"id":29,"seat":0},{"id":32,"seat":0},{"id":41,"seat":0},{"id":44,"seat":0},{"id":46,"seat":0},{"id":59,"seat":0},{"id":61,"seat":0},{"id":62,"seat":0},{"id":64,"seat":0},{"id":67,"seat":0},{"id":70,"seat":0},{"id":73,"seat":0},{"id":74,"seat":0},{"id":76,"seat":0},{"id":77,"seat":0},{"id":87,"seat":0},{"id":92,"seat":0},{"id":93,"seat":0},{"id":94,"seat":0},{"id":95,"seat":0},{"id":98,"seat":0},{"id":100,"seat":0},{"id":107,"seat":0},{"id":111,"seat":0},{"id":117,"seat":0},{"id":119,"seat":0},{"id":122,"seat":0},{"id":124,"seat":0},{"id":125,"seat":0},{"id":126,"seat":0},{"id":127,"seat":0},{"id":128,"seat":0},{"id":129,"seat":0},{"id":130,"seat":0},{"id":133,"seat":0},{"id":136,"seat":0},{"id":137,"seat":0},{"id":138,"seat":0},{"id":139,"seat":0},{"id":140,"seat":0},{"id":141,"seat":0},{"id":142,"seat":0},{"id":144,"seat":0},{"id":161,"seat":0},{"id":168,"seat":0},{"id":170,"seat":0}],"areas":[{"id":171,"name":"นครปฐม เขต 1","areaNo":1,"candidates":[{"id":1518,"candidateAreaNo":2,"firstName":"ศุภโชค","lastName":"ศรีสุขจร","party":"ชาติไทยพัฒนา","partyId":162,"goodVote":39899},{"id":1517,"candidateAreaNo":1,"firstName":"จารุพรรณ","lastName":"เพชรดี","party":"ก้าวไกล","partyId":116,"goodVote":27106}]},{"id":172,"name":"นครปฐม เขต 2","areaNo":2,"candidates":[{"id":1532,"candidateAreaNo":4,"firstName":"สินธพ","lastName":"แก้วพิจิตร","party":"รวมไทยสร้างชาติ","partyId":121,"goodVote":33770},{"id":1534,"candidateAreaNo":6,"firstName":"ศศนันท์","lastName":"รัตนบรรเทิง","party":"ก้าวไกล","partyId":116,"goodVote":32056}]},{"id":173,"name":"นครปฐม เขต 3","areaNo":3,"candidates":[{"id":1542,"candidateAreaNo":5,"firstName":"พาณุวัฒณ์","lastName":"สะสมทรัพย์","party":"ชาติไทยพัฒนา","partyId":162,"goodVote":42825},{"id":1540,"candidateAreaNo":3,"firstName":"ภาชินี","lastName":"เหลืองเพิ่มสกุล","party":"ก้าวไกล","partyId":116,"goodVote":24814}]},{"id":174,"name":"นครปฐม เขต 4","areaNo":4,"candidates":[{"id":1553,"candidateAreaNo":6,"firstName":"กิตติภณ","lastName":"ปานพรหมมาศ","party":"ก้าวไกล","partyId":116,"goodVote":24898},{"id":1551,"candidateAreaNo":4,"firstName":"ก่อเกียรติ","lastName":"สิริยะเสถียร","party":"ชาติไทยพัฒนา","partyId":162,"goodVote":19861}]},{"id":175,"name":"นครปฐม เขต 5","areaNo":5,"candidates":[{"id":1562,"candidateAreaNo":4,"firstName":"อนุชา","lastName":"สะสมทรัพย์","party":"ชาติไทยพัฒนา","partyId":162,"goodVote":36422},{"id":1561,"candidateAreaNo":3,"firstName":"สาโรจน์","lastName":"จุ้ยเจริญ","party":"ก้าวไกล","partyId":116,"goodVote":24896}]},{"id":176,"name":"นครปฐม เขต 6","areaNo":6,"candidates":[{"id":1576,"candidateAreaNo":8,"firstName":"ชิษณุพงศ์","lastName":"ตั้งเมธากุล","party":"ก้าวไกล","partyId":116,"goodVote":38812},{"id":1575,"candidateAreaNo":7,"firstName":"เผดิมชัย","lastName":"สะสมทรัพย์","party":"ชาติไทยพัฒนา","partyId":162,"goodVote":19742}]}]}